nmrtools.py
nmrtools-0.1.0.dist-info/METADATA
nmrtools-0.1.0.dist-info/WHEEL
nmrtools-0.1.0.dist-info/entry_points.txt
nmrtools-0.1.0.dist-info/top_level.txt
nmrtools-0.1.0.dist-info/RECORD
