Metadata-Version: 2.1
Name: nmrtools
Version: 0.1.0
Summary: A package for NMR data processing
Home-page: https://github.com/pratiman-de/Bruker-to-Numpy
Author: pratiman-de
License: MIT
Platform: UNKNOWN
Requires-Dist: Click
Requires-Dist: numpy
